{
  "name": "t:sections.footer.name",
  "type": "footer",
  "sections": {
    "footer": {
      "type": "footer",
      "blocks": {
        "link_list_N9irQR": {
          "type": "link_list",
          "settings": {
            "heading": "Search",
            "menu": "footer"
          }
        },
        "link_list_QPVMtg": {
          "type": "link_list",
          "settings": {
            "heading": "Quick links",
            "menu": "main-menu"
          }
        },
        "link_list_9MKtJR": {
          "type": "link_list",
          "settings": {
            "heading": "<a href=\"https:\/\/www.facebook.com\/\" target=\"_blank\">Facebook<\/a>",
            "menu": ""
          }
        },
        "link_list_wYXnyk": {
          "type": "link_list",
          "settings": {
            "heading": "<a href=\"https:\/\/www.instagram.com\/\" target=\"_blank\">Instagram<\/a>",
            "menu": ""
          }
        },
        "text_XinjkP": {
          "type": "text",
          "settings": {
            "heading": "Contact",
            "subtext": "<p>385 Noah Place Suite <\/p><p>878info@form.com\u2028<\/p><p>877-255-7945<\/p>"
          }
        },
        "image_EMxnLD": {
          "type": "image",
          "settings": {
            "image": "shopify:\/\/shop_images\/SeekPng.com_instagram-png-logo_29915.png",
            "image_width": 170,
            "alignment": ""
          }
        }
      },
      "block_order": [
        "link_list_N9irQR",
        "link_list_QPVMtg",
        "link_list_9MKtJR",
        "link_list_wYXnyk",
        "text_XinjkP",
        "image_EMxnLD"
      ],
      "settings": {
        "color_scheme": "scheme-3",
        "newsletter_enable": true,
        "newsletter_heading": "Subscribe to our emails",
        "enable_follow_on_shop": true,
        "show_social": true,
        "enable_country_selector": true,
        "enable_language_selector": true,
        "payment_enable": true,
        "show_policy": false,
        "margin_top": 0,
        "padding_top": 36,
        "padding_bottom": 36
      }
    }
  },
  "order": [
    "footer"
  ]
}
